[
  {
    "word": "adjust",
    "translation": "v.调整，调节",
    "unit": "Unit_4_Sub3",
    "status": {
      "memorized_past": false,
      "memorized_today": false,
      "last_reviewed": null,
      "review_count": 0
    },
    "notes": "",
    "pos": null,
    "definitions": [],
    "example_sentences": []
  },
  {
    "word": "adjustment",
    "translation": "n.调整，调节",
    "unit": "Unit_4_Sub3",
    "status": {
      "memorized_past": false,
      "memorized_today": false,
      "last_reviewed": null,
      "review_count": 0
    },
    "notes": "",
    "pos": null,
    "definitions": [],
    "example_sentences": []
  },
  {
    "word": "angle",
    "translation": "n.角度;观点",
    "unit": "Unit_4_Sub3",
    "status": {
      "memorized_past": false,
      "memorized_today": false,
      "last_reviewed": null,
      "review_count": 0
    },
    "notes": "",
    "pos": null,
    "definitions": [],
    "example_sentences": []
  },
  {
    "word": "angle",
    "translation": "n.角度",
    "unit": "Unit_4_Sub3",
    "status": {
      "memorized_past": false,
      "memorized_today": false,
      "last_reviewed": null,
      "review_count": 0
    },
    "notes": "",
    "pos": null,
    "definitions": [],
    "example_sentences": []
  },
  {
    "word": "backward",
    "translation": "adv.向后地",
    "unit": "Unit_4_Sub3",
    "status": {
      "memorized_past": false,
      "memorized_today": false,
      "last_reviewed": null,
      "review_count": 0
    },
    "notes": "",
    "pos": null,
    "definitions": [],
    "example_sentences": []
  },
  {
    "word": "balance",
    "translation": "n.天平;平衡",
    "unit": "Unit_4_Sub3",
    "status": {
      "memorized_past": false,
      "memorized_today": false,
      "last_reviewed": null,
      "review_count": 0
    },
    "notes": "",
    "pos": null,
    "definitions": [],
    "example_sentences": []
  },
  {
    "word": "behind",
    "translation": "prep.在...后面",
    "unit": "Unit_4_Sub3",
    "status": {
      "memorized_past": false,
      "memorized_today": false,
      "last_reviewed": null,
      "review_count": 0
    },
    "notes": "",
    "pos": null,
    "definitions": [],
    "example_sentences": []
  },
  {
    "word": "bend",
    "translation": "v.弯曲;屈服",
    "unit": "Unit_4_Sub3",
    "status": {
      "memorized_past": false,
      "memorized_today": false,
      "last_reviewed": null,
      "review_count": 0
    },
    "notes": "",
    "pos": null,
    "definitions": [],
    "example_sentences": []
  },
  {
    "word": "bottom",
    "translation": "n.底部;底",
    "unit": "Unit_4_Sub3",
    "status": {
      "memorized_past": false,
      "memorized_today": false,
      "last_reviewed": null,
      "review_count": 0
    },
    "notes": "",
    "pos": null,
    "definitions": [],
    "example_sentences": []
  },
  {
    "word": "climb",
    "translation": "v.攀登;爬升",
    "unit": "Unit_4_Sub3",
    "status": {
      "memorized_past": false,
      "memorized_today": false,
      "last_reviewed": null,
      "review_count": 0
    },
    "notes": "",
    "pos": null,
    "definitions": [],
    "example_sentences": []
  },
  {
    "word": "clockwise",
    "translation": "adj./adv.顺时针方向（的）",
    "unit": "Unit_4_Sub3",
    "status": {
      "memorized_past": false,
      "memorized_today": false,
      "last_reviewed": null,
      "review_count": 0
    },
    "notes": "",
    "pos": null,
    "definitions": [],
    "example_sentences": []
  },
  {
    "word": "descend",
    "translation": "v.下降;下去",
    "unit": "Unit_4_Sub3",
    "status": {
      "memorized_past": false,
      "memorized_today": false,
      "last_reviewed": null,
      "review_count": 0
    },
    "notes": "",
    "pos": null,
    "definitions": [],
    "example_sentences": []
  },
  {
    "word": "descent",
    "translation": "n.下降;血统",
    "unit": "Unit_4_Sub3",
    "status": {
      "memorized_past": false,
      "memorized_today": false,
      "last_reviewed": null,
      "review_count": 0
    },
    "notes": "",
    "pos": null,
    "definitions": [],
    "example_sentences": []
  },
  {
    "word": "direction",
    "translation": "n.方向;指导",
    "unit": "Unit_4_Sub3",
    "status": {
      "memorized_past": false,
      "memorized_today": false,
      "last_reviewed": null,
      "review_count": 0
    },
    "notes": "",
    "pos": null,
    "definitions": [],
    "example_sentences": []
  },
  {
    "word": "down",
    "translation": "adv.向下",
    "unit": "Unit_4_Sub3",
    "status": {
      "memorized_past": false,
      "memorized_today": false,
      "last_reviewed": null,
      "review_count": 0
    },
    "notes": "",
    "pos": null,
    "definitions": [],
    "example_sentences": []
  },
  {
    "word": "down",
    "translation": "adv.向下;沿着",
    "unit": "Unit_4_Sub3",
    "status": {
      "memorized_past": false,
      "memorized_today": false,
      "last_reviewed": null,
      "review_count": 0
    },
    "notes": "",
    "pos": null,
    "definitions": [],
    "example_sentences": []
  },
  {
    "word": "embankment",
    "translation": "n.路堤;堤岸",
    "unit": "Unit_4_Sub3",
    "status": {
      "memorized_past": false,
      "memorized_today": false,
      "last_reviewed": null,
      "review_count": 0
    },
    "notes": "",
    "pos": null,
    "definitions": [],
    "example_sentences": []
  },
  {
    "word": "fall",
    "translation": "v.落下;跌倒",
    "unit": "Unit_4_Sub3",
    "status": {
      "memorized_past": false,
      "memorized_today": false,
      "last_reviewed": null,
      "review_count": 0
    },
    "notes": "",
    "pos": null,
    "definitions": [],
    "example_sentences": []
  },
  {
    "word": "fallen",
    "translation": "adj.倒下的;堕落的",
    "unit": "Unit_4_Sub3",
    "status": {
      "memorized_past": false,
      "memorized_today": false,
      "last_reviewed": null,
      "review_count": 0
    },
    "notes": "",
    "pos": null,
    "definitions": [],
    "example_sentences": []
  },
  {
    "word": "flat",
    "translation": "adj.平坦的",
    "unit": "Unit_4_Sub3",
    "status": {
      "memorized_past": false,
      "memorized_today": false,
      "last_reviewed": null,
      "review_count": 0
    },
    "notes": "",
    "pos": null,
    "definitions": [],
    "example_sentences": []
  },
  {
    "word": "float",
    "translation": "v.浮动;漂浮",
    "unit": "Unit_4_Sub3",
    "status": {
      "memorized_past": false,
      "memorized_today": false,
      "last_reviewed": null,
      "review_count": 0
    },
    "notes": "",
    "pos": null,
    "definitions": [],
    "example_sentences": []
  },
  {
    "word": "front",
    "translation": "adj.前面的",
    "unit": "Unit_4_Sub3",
    "status": {
      "memorized_past": false,
      "memorized_today": false,
      "last_reviewed": null,
      "review_count": 0
    },
    "notes": "",
    "pos": null,
    "definitions": [],
    "example_sentences": []
  },
  {
    "word": "gradual",
    "translation": "adj.逐渐的;逐步的",
    "unit": "Unit_4_Sub3",
    "status": {
      "memorized_past": false,
      "memorized_today": false,
      "last_reviewed": null,
      "review_count": 0
    },
    "notes": "",
    "pos": null,
    "definitions": [],
    "example_sentences": []
  },
  {
    "word": "ground",
    "translation": "n.地面;理由",
    "unit": "Unit_4_Sub3",
    "status": {
      "memorized_past": false,
      "memorized_today": false,
      "last_reviewed": null,
      "review_count": 0
    },
    "notes": "",
    "pos": null,
    "definitions": [],
    "example_sentences": []
  },
  {
    "word": "horizontal",
    "translation": "adj.水平的;横向的",
    "unit": "Unit_4_Sub3",
    "status": {
      "memorized_past": false,
      "memorized_today": false,
      "last_reviewed": null,
      "review_count": 0
    },
    "notes": "",
    "pos": null,
    "definitions": [],
    "example_sentences": []
  },
  {
    "word": "incline",
    "translation": "v.使倾斜;倾向于",
    "unit": "Unit_4_Sub3",
    "status": {
      "memorized_past": false,
      "memorized_today": false,
      "last_reviewed": null,
      "review_count": 0
    },
    "notes": "",
    "pos": null,
    "definitions": [],
    "example_sentences": []
  },
  {
    "word": "inward",
    "translation": "adj.向内的;内部的",
    "unit": "Unit_4_Sub3",
    "status": {
      "memorized_past": false,
      "memorized_today": false,
      "last_reviewed": null,
      "review_count": 0
    },
    "notes": "",
    "pos": null,
    "definitions": [],
    "example_sentences": []
  },
  {
    "word": "lay",
    "translation": "v.放;产卵",
    "unit": "Unit_4_Sub3",
    "status": {
      "memorized_past": false,
      "memorized_today": false,
      "last_reviewed": null,
      "review_count": 0
    },
    "notes": "",
    "pos": null,
    "definitions": [],
    "example_sentences": []
  },
  {
    "word": "layoff",
    "translation": "n.解雇;失业",
    "unit": "Unit_4_Sub3",
    "status": {
      "memorized_past": false,
      "memorized_today": false,
      "last_reviewed": null,
      "review_count": 0
    },
    "notes": "",
    "pos": null,
    "definitions": [],
    "example_sentences": []
  },
  {
    "word": "margin",
    "translation": "n.边缘;利润",
    "unit": "Unit_4_Sub3",
    "status": {
      "memorized_past": false,
      "memorized_today": false,
      "last_reviewed": null,
      "review_count": 0
    },
    "notes": "",
    "pos": null,
    "definitions": [],
    "example_sentences": []
  },
  {
    "word": "orient",
    "translation": "v.定位;定方向",
    "unit": "Unit_4_Sub3",
    "status": {
      "memorized_past": false,
      "memorized_today": false,
      "last_reviewed": null,
      "review_count": 0
    },
    "notes": "",
    "pos": null,
    "definitions": [],
    "example_sentences": []
  },
  {
    "word": "orientation",
    "translation": "n.方向;定位",
    "unit": "Unit_4_Sub3",
    "status": {
      "memorized_past": false,
      "memorized_today": false,
      "last_reviewed": null,
      "review_count": 0
    },
    "notes": "",
    "pos": null,
    "definitions": [],
    "example_sentences": []
  },
  {
    "word": "outward",
    "translation": "adj.向外的",
    "unit": "Unit_4_Sub3",
    "status": {
      "memorized_past": false,
      "memorized_today": false,
      "last_reviewed": null,
      "review_count": 0
    },
    "notes": "",
    "pos": null,
    "definitions": [],
    "example_sentences": []
  },
  {
    "word": "overflow",
    "translation": "v.溢出;充满",
    "unit": "Unit_4_Sub3",
    "status": {
      "memorized_past": false,
      "memorized_today": false,
      "last_reviewed": null,
      "review_count": 0
    },
    "notes": "",
    "pos": null,
    "definitions": [],
    "example_sentences": []
  },
  {
    "word": "overturn",
    "translation": "v.推翻;倾覆",
    "unit": "Unit_4_Sub3",
    "status": {
      "memorized_past": false,
      "memorized_today": false,
      "last_reviewed": null,
      "review_count": 0
    },
    "notes": "",
    "pos": null,
    "definitions": [],
    "example_sentences": []
  },
  {
    "word": "position",
    "translation": "n.位置;职位",
    "unit": "Unit_4_Sub3",
    "status": {
      "memorized_past": false,
      "memorized_today": false,
      "last_reviewed": null,
      "review_count": 0
    },
    "notes": "",
    "pos": null,
    "definitions": [],
    "example_sentences": []
  },
  {
    "word": "rise",
    "translation": "n.上升",
    "unit": "Unit_4_Sub3",
    "status": {
      "memorized_past": false,
      "memorized_today": false,
      "last_reviewed": null,
      "review_count": 0
    },
    "notes": "",
    "pos": null,
    "definitions": [],
    "example_sentences": []
  },
  {
    "word": "rotate",
    "translation": "v.旋转;轮流",
    "unit": "Unit_4_Sub3",
    "status": {
      "memorized_past": false,
      "memorized_today": false,
      "last_reviewed": null,
      "review_count": 0
    },
    "notes": "",
    "pos": null,
    "definitions": [],
    "example_sentences": []
  },
  {
    "word": "round",
    "translation": "adj.圆的",
    "unit": "Unit_4_Sub3",
    "status": {
      "memorized_past": false,
      "memorized_today": false,
      "last_reviewed": null,
      "review_count": 0
    },
    "notes": "",
    "pos": null,
    "definitions": [],
    "example_sentences": []
  },
  {
    "word": "shaky",
    "translation": "adj.不稳定的;不可靠的",
    "unit": "Unit_4_Sub3",
    "status": {
      "memorized_past": false,
      "memorized_today": false,
      "last_reviewed": null,
      "review_count": 0
    },
    "notes": "",
    "pos": null,
    "definitions": [],
    "example_sentences": []
  },
  {
    "word": "sideways",
    "translation": "adv.斜着;向一边",
    "unit": "Unit_4_Sub3",
    "status": {
      "memorized_past": false,
      "memorized_today": false,
      "last_reviewed": null,
      "review_count": 0
    },
    "notes": "",
    "pos": null,
    "definitions": [],
    "example_sentences": []
  },
  {
    "word": "sit",
    "translation": "v.坐;位于",
    "unit": "Unit_4_Sub3",
    "status": {
      "memorized_past": false,
      "memorized_today": false,
      "last_reviewed": null,
      "review_count": 0
    },
    "notes": "",
    "pos": null,
    "definitions": [],
    "example_sentences": []
  },
  {
    "word": "sitting",
    "translation": "n.会议;座位",
    "unit": "Unit_4_Sub3",
    "status": {
      "memorized_past": false,
      "memorized_today": false,
      "last_reviewed": null,
      "review_count": 0
    },
    "notes": "",
    "pos": null,
    "definitions": [],
    "example_sentences": []
  },
  {
    "word": "sitting",
    "translation": "room",
    "unit": "Unit_4_Sub3",
    "status": {
      "memorized_past": false,
      "memorized_today": false,
      "last_reviewed": null,
      "review_count": 0
    },
    "notes": "",
    "pos": null,
    "definitions": [],
    "example_sentences": []
  },
  {
    "word": "skew",
    "translation": "adj.斜的",
    "unit": "Unit_4_Sub3",
    "status": {
      "memorized_past": false,
      "memorized_today": false,
      "last_reviewed": null,
      "review_count": 0
    },
    "notes": "",
    "pos": null,
    "definitions": [],
    "example_sentences": []
  },
  {
    "word": "slant",
    "translation": "n.倾斜;斜面",
    "unit": "Unit_4_Sub3",
    "status": {
      "memorized_past": false,
      "memorized_today": false,
      "last_reviewed": null,
      "review_count": 0
    },
    "notes": "",
    "pos": null,
    "definitions": [],
    "example_sentences": []
  },
  {
    "word": "slope",
    "translation": "n.斜坡;倾斜",
    "unit": "Unit_4_Sub3",
    "status": {
      "memorized_past": false,
      "memorized_today": false,
      "last_reviewed": null,
      "review_count": 0
    },
    "notes": "",
    "pos": null,
    "definitions": [],
    "example_sentences": []
  },
  {
    "word": "sloping",
    "translation": "adj.倾斜的",
    "unit": "Unit_4_Sub3",
    "status": {
      "memorized_past": false,
      "memorized_today": false,
      "last_reviewed": null,
      "review_count": 0
    },
    "notes": "",
    "pos": null,
    "definitions": [],
    "example_sentences": []
  },
  {
    "word": "slump",
    "translation": "n.暴跌;低潮期",
    "unit": "Unit_4_Sub3",
    "status": {
      "memorized_past": false,
      "memorized_today": false,
      "last_reviewed": null,
      "review_count": 0
    },
    "notes": "",
    "pos": null,
    "definitions": [],
    "example_sentences": []
  },
  {
    "word": "squabble",
    "translation": "n.争吵;口角",
    "unit": "Unit_4_Sub3",
    "status": {
      "memorized_past": false,
      "memorized_today": false,
      "last_reviewed": null,
      "review_count": 0
    },
    "notes": "",
    "pos": null,
    "definitions": [],
    "example_sentences": []
  },
  {
    "word": "stability",
    "translation": "n.稳定;稳定性",
    "unit": "Unit_4_Sub3",
    "status": {
      "memorized_past": false,
      "memorized_today": false,
      "last_reviewed": null,
      "review_count": 0
    },
    "notes": "",
    "pos": null,
    "definitions": [],
    "example_sentences": []
  },
  {
    "word": "stake",
    "translation": "n.桩;赌注",
    "unit": "Unit_4_Sub3",
    "status": {
      "memorized_past": false,
      "memorized_today": false,
      "last_reviewed": null,
      "review_count": 0
    },
    "notes": "",
    "pos": null,
    "definitions": [],
    "example_sentences": []
  },
  {
    "word": "stance",
    "translation": "n.立场;位置",
    "unit": "Unit_4_Sub3",
    "status": {
      "memorized_past": false,
      "memorized_today": false,
      "last_reviewed": null,
      "review_count": 0
    },
    "notes": "",
    "pos": null,
    "definitions": [],
    "example_sentences": []
  },
  {
    "word": "stand",
    "translation": "v.站立;经受",
    "unit": "Unit_4_Sub3",
    "status": {
      "memorized_past": false,
      "memorized_today": false,
      "last_reviewed": null,
      "review_count": 0
    },
    "notes": "",
    "pos": null,
    "definitions": [],
    "example_sentences": []
  },
  {
    "word": "steep",
    "translation": "adj.陡峭的",
    "unit": "Unit_4_Sub3",
    "status": {
      "memorized_past": false,
      "memorized_today": false,
      "last_reviewed": null,
      "review_count": 0
    },
    "notes": "",
    "pos": null,
    "definitions": [],
    "example_sentences": []
  },
  {
    "word": "steeple",
    "translation": "n.尖塔;塔楼",
    "unit": "Unit_4_Sub3",
    "status": {
      "memorized_past": false,
      "memorized_today": false,
      "last_reviewed": null,
      "review_count": 0
    },
    "notes": "",
    "pos": null,
    "definitions": [],
    "example_sentences": []
  },
  {
    "word": "stem",
    "translation": "n.茎;词干",
    "unit": "Unit_4_Sub3",
    "status": {
      "memorized_past": false,
      "memorized_today": false,
      "last_reviewed": null,
      "review_count": 0
    },
    "notes": "",
    "pos": null,
    "definitions": [],
    "example_sentences": []
  },
  {
    "word": "straight",
    "translation": "adj.直的",
    "unit": "Unit_4_Sub3",
    "status": {
      "memorized_past": false,
      "memorized_today": false,
      "last_reviewed": null,
      "review_count": 0
    },
    "notes": "",
    "pos": null,
    "definitions": [],
    "example_sentences": []
  },
  {
    "word": "sunken",
    "translation": "adj.沉没的;塌陷的",
    "unit": "Unit_4_Sub3",
    "status": {
      "memorized_past": false,
      "memorized_today": false,
      "last_reviewed": null,
      "review_count": 0
    },
    "notes": "",
    "pos": null,
    "definitions": [],
    "example_sentences": []
  },
  {
    "word": "surface",
    "translation": "n.表面;表层",
    "unit": "Unit_4_Sub3",
    "status": {
      "memorized_past": false,
      "memorized_today": false,
      "last_reviewed": null,
      "review_count": 0
    },
    "notes": "",
    "pos": null,
    "definitions": [],
    "example_sentences": []
  },
  {
    "word": "suspend",
    "translation": "v.暂停;悬挂",
    "unit": "Unit_4_Sub3",
    "status": {
      "memorized_past": false,
      "memorized_today": false,
      "last_reviewed": null,
      "review_count": 0
    },
    "notes": "",
    "pos": null,
    "definitions": [],
    "example_sentences": []
  },
  {
    "word": "tilt",
    "translation": "v.倾斜;倾倒",
    "unit": "Unit_4_Sub3",
    "status": {
      "memorized_past": false,
      "memorized_today": false,
      "last_reviewed": null,
      "review_count": 0
    },
    "notes": "",
    "pos": null,
    "definitions": [],
    "example_sentences": []
  },
  {
    "word": "towards",
    "translation": "prep.向;朝",
    "unit": "Unit_4_Sub3",
    "status": {
      "memorized_past": false,
      "memorized_today": false,
      "last_reviewed": null,
      "review_count": 0
    },
    "notes": "",
    "pos": null,
    "definitions": [],
    "example_sentences": []
  },
  {
    "word": "turn",
    "translation": "v.转动",
    "unit": "Unit_4_Sub3",
    "status": {
      "memorized_past": false,
      "memorized_today": false,
      "last_reviewed": null,
      "review_count": 0
    },
    "notes": "",
    "pos": null,
    "definitions": [],
    "example_sentences": []
  },
  {
    "word": "turning",
    "translation": "n.转弯;转变",
    "unit": "Unit_4_Sub3",
    "status": {
      "memorized_past": false,
      "memorized_today": false,
      "last_reviewed": null,
      "review_count": 0
    },
    "notes": "",
    "pos": null,
    "definitions": [],
    "example_sentences": []
  },
  {
    "word": "underline",
    "translation": "v.强调;在...下划线",
    "unit": "Unit_4_Sub3",
    "status": {
      "memorized_past": false,
      "memorized_today": false,
      "last_reviewed": null,
      "review_count": 0
    },
    "notes": "",
    "pos": null,
    "definitions": [],
    "example_sentences": []
  },
  {
    "word": "unsteady",
    "translation": "adj.不稳定的;不稳固的",
    "unit": "Unit_4_Sub3",
    "status": {
      "memorized_past": false,
      "memorized_today": false,
      "last_reviewed": null,
      "review_count": 0
    },
    "notes": "",
    "pos": null,
    "definitions": [],
    "example_sentences": []
  },
  {
    "word": "uplift",
    "translation": "v.抬起;鼓舞",
    "unit": "Unit_4_Sub3",
    "status": {
      "memorized_past": false,
      "memorized_today": false,
      "last_reviewed": null,
      "review_count": 0
    },
    "notes": "",
    "pos": null,
    "definitions": [],
    "example_sentences": []
  },
  {
    "word": "upright",
    "translation": "adj.直立的;正直的",
    "unit": "Unit_4_Sub3",
    "status": {
      "memorized_past": false,
      "memorized_today": false,
      "last_reviewed": null,
      "review_count": 0
    },
    "notes": "",
    "pos": null,
    "definitions": [],
    "example_sentences": []
  },
  {
    "word": "upturn",
    "translation": "n.好转;上升趋势",
    "unit": "Unit_4_Sub3",
    "status": {
      "memorized_past": false,
      "memorized_today": false,
      "last_reviewed": null,
      "review_count": 0
    },
    "notes": "",
    "pos": null,
    "definitions": [],
    "example_sentences": []
  },
  {
    "word": "upward",
    "translation": "adj.向上的",
    "unit": "Unit_4_Sub3",
    "status": {
      "memorized_past": false,
      "memorized_today": false,
      "last_reviewed": null,
      "review_count": 0
    },
    "notes": "",
    "pos": null,
    "definitions": [],
    "example_sentences": []
  },
  {
    "word": "wayside",
    "translation": "n.路边;路旁",
    "unit": "Unit_4_Sub3",
    "status": {
      "memorized_past": false,
      "memorized_today": false,
      "last_reviewed": null,
      "review_count": 0
    },
    "notes": "",
    "pos": null,
    "definitions": [],
    "example_sentences": []
  },
  {
    "word": "windy",
    "translation": "adj.有风的;多风的",
    "unit": "Unit_4_Sub3",
    "status": {
      "memorized_past": false,
      "memorized_today": false,
      "last_reviewed": null,
      "review_count": 0
    },
    "notes": "",
    "pos": null,
    "definitions": [],
    "example_sentences": []
  }
]